README.md
setup.py
flight/__init__.py
flight/exceptions.py
flight/utils.py
flight/cli/__init__.py
flightpy.egg-info/PKG-INFO
flightpy.egg-info/SOURCES.txt
flightpy.egg-info/dependency_links.txt
flightpy.egg-info/entry_points.txt
flightpy.egg-info/requires.txt
flightpy.egg-info/top_level.txt