Metadata-Version: 2.1
Name: flightpy
Version: 0.0.0.post4
Summary: a modern python web framework with super powers
Home-page: https://github.com/dsikes/flight
Author: Dan Sikes
Author-email: dansikes7@gmail.com
License: UNKNOWN
Project-URL: Source, https://github.com/dsikes/flight
Keywords: python,framework,web framework
Platform: UNKNOWN
